fastmlx/__init__.py
fastmlx/fastmlx.py
fastmlx/utils.py
fastmlx/tools/arcee_agent.j2
fastmlx/tools/command-r-plus.j2
fastmlx/tools/config.json
fastmlx/tools/llama-3_1.j2
fastmlx/tools/xlam.j2
fastmlx/types/model.py
fastmlx/types/chat/chat_completion.py
fastmlxOns-0.2.1.dist-info/AUTHORS.rst
fastmlxOns-0.2.1.dist-info/LICENSE
fastmlxOns-0.2.1.dist-info/METADATA
fastmlxOns-0.2.1.dist-info/WHEEL
fastmlxOns-0.2.1.dist-info/entry_points.txt
fastmlxOns-0.2.1.dist-info/top_level.txt
fastmlxOns-0.2.1.dist-info/RECORD
