Metadata-Version: 2.1
Name: fastmlxOns
Version: 0.2.1
Summary: FastMLX is a high performance production ready API to host MLX models.
Author-email: Prince Canuma <prince.gdt@gmail.com>
License: Apache Software License 2.0
Project-URL: Homepage, https://github.com/Blaizzy/fastmlx
Keywords: fastmlx,MLX,Apple MLX,vision language models,VLMs,large language models,LLMs
Classifier: Intended Audience :: Developers
Classifier: License :: OSI Approved :: Apache Software License
Classifier: Natural Language :: English
Classifier: Programming Language :: Python :: 3.8
Classifier: Programming Language :: Python :: 3.9
Classifier: Programming Language :: Python :: 3.10
Classifier: Programming Language :: Python :: 3.11
Classifier: Programming Language :: Python :: 3.12
Requires-Python: >=3.8
License-File: LICENSE
License-File: AUTHORS.rst
Requires-Dist: mlx >=0.15
Requires-Dist: mlx-lm >=0.15.2
Requires-Dist: mlx-vlm >=0.0.12
Requires-Dist: fastapi >=0.111.0
Requires-Dist: jinja2
Provides-Extra: all
Requires-Dist: fastmlx[extra] ; extra == 'all'
Provides-Extra: extra
